README.md
setup.cfg
setup.py
face_classification/__init__.py
face_classification/classifier.py
face_classification/face_clustering.py
face_classification/recognition_server.py
face_classification/stream.py
face_classification/train.py
face_classification/view_stream.py
face_classification.egg-info/PKG-INFO
face_classification.egg-info/SOURCES.txt
face_classification.egg-info/dependency_links.txt
face_classification.egg-info/not-zip-safe
face_classification.egg-info/requires.txt
face_classification.egg-info/top_level.txt