Metadata-Version: 1.0
Name: face-classification
Version: 0.0.6
Summary: Train and classifiy faces from images using deep learning. https://gitlab.lftechnology.com/leapfrogai/face-classification/
Home-page: UNKNOWN
Author: Leapfrog Technology INC
Author-email: UNKNOWN
License: Apache License 2.0
Platform: UNKNOWN
